pycocotools/__init__.py
pycocotools/_mask.cp311-win_amd64.pyd
pycocotools/coco.py
pycocotools/cocoeval.py
pycocotools/mask.py
aiartchan_pycocotools-2.0.6.dist-info/METADATA
aiartchan_pycocotools-2.0.6.dist-info/WHEEL
aiartchan_pycocotools-2.0.6.dist-info/top_level.txt
aiartchan_pycocotools-2.0.6.dist-info/RECORD
