Metadata-Version: 2.1
Name: aiartchan-pycocotools
Version: 2.0.6
Summary: Official APIs for the MS-COCO dataset
Home-page: https://github.com/ppwwyyxx/cocoapi
License: FreeBSD
Requires-Python: >=3.5
Requires-Dist: matplotlib (>=2.1.0)
Requires-Dist: numpy
